sas_to_polars/__init__.py
sas_to_polars/sas_to_polars.py
sas_to_polars-1.0.0.dist-info/licenses/LICENSE
sas_to_polars-1.0.0.dist-info/METADATA
sas_to_polars-1.0.0.dist-info/WHEEL
sas_to_polars-1.0.0.dist-info/top_level.txt
sas_to_polars-1.0.0.dist-info/RECORD
