Metadata-Version: 2.4
Name: sas-to-polars
Version: 1.0.0
Summary: Convert SAS datasets (.sas7bdat files) to Polars DataFrames.
Author-email: Samuel E Edwards <elijah.edwards41@gmail.com>
License: MIT License
Project-URL: Homepage, https://github.com/samuel-elijah-edwards/sas-to-polars
Project-URL: Bug Tracker, https://github.com/samuel-elijah-edwards/sas-to-polars/issues
Keywords: sas,polars,data conversion,data processing
Classifier: Programming Language :: Python :: 3
Classifier: License :: OSI Approved :: MIT License
Classifier: Operating System :: OS Independent
Requires-Python: >=3.10
License-File: LICENSE
Requires-Dist: pyreadstat>=0.12.0
Requires-Dist: polars>=0.20.0
Requires-Dist: pyarrow>=10.0.0
Dynamic: license-file
